anthologist/__init__.py
anthologist/helpers.py
anthologist/main.py
anthologist-0.0.4.dist-info/entry_points.txt
anthologist-0.0.4.dist-info/METADATA
anthologist-0.0.4.dist-info/WHEEL
anthologist-0.0.4.dist-info/RECORD
