Metadata-Version: 2.1
Name: anthologist
Version: 0.0.4
Summary: A CLI for managing multiple Poetry-managed Python projects simultaneously
Home-page: https://github.com/jharibo/anthologist
Keywords: poetry,packaging
Author: James Harrison
Author-email: 40500443+jharibo@users.noreply.github.com
Requires-Python: >=3.10,<4.0
Classifier: Programming Language :: Python :: 3
Classifier: Programming Language :: Python :: 3.10
Classifier: Programming Language :: Python :: 3.11
Classifier: Programming Language :: Python :: 3.12
Requires-Dist: click (>=8.1.7,<9.0.0)
Project-URL: Repository, https://github.com/jharibo/anthologist
